<?xml version="1.0" encoding="UTF-8"?>
<objects serializationModel="Studio.02.00.00">
	<object class="AudioFile" id="{7f10fb58-ad37-4ae6-bc08-2203141e9036}">
		<property name="assetPath">
			<value>Animal, Insect, Spider, Scuttle, Undergrowth, Leaves, Dirt 2 SND14758.wav</value>
		</property>
		<property name="frequencyInKHz">
			<value>96</value>
		</property>
		<property name="channelCount">
			<value>2</value>
		</property>
		<property name="length">
			<value>3.7576874999999998</value>
		</property>
		<relationship name="masterAssetFolder">
			<destination>{b650f45d-ec8f-45e3-9658-d2c44caa3cf1}</destination>
		</relationship>
	</object>
</objects>
